shepherd/__init__.py
shepherd/_cmdline.py
shepherd/cmdline.py
shepherd/errors.py
shepherd/formatting.py
shepherd/inventory.py
shepherd/provider.py
shepherd/aws/__init__.py
shepherd/aws/cmdline.py
shepherd/utils/__init__.py
shepherd/utils/cmdline_controller.py
shepherd/utils/messages.py
cloud_shepherd-2.0.6.dist-info/COPYING
cloud_shepherd-2.0.6.dist-info/LICENSE
cloud_shepherd-2.0.6.dist-info/METADATA
cloud_shepherd-2.0.6.dist-info/WHEEL
cloud_shepherd-2.0.6.dist-info/entry_points.txt
cloud_shepherd-2.0.6.dist-info/top_level.txt
cloud_shepherd-2.0.6.dist-info/RECORD
