Metadata-Version: 2.1
Name: cloud-shepherd
Version: 2.0.6
Summary: Control cloud servers using the provider's API
Home-page: https://github.com/unixnut/shepherd
Author: Alastair Irvine
License: GNU General Public License v3
Keywords: a,w,s, ,e,c,2, ,c,l,i
Classifier: Development Status :: 4 - Beta
Classifier: Intended Audience :: End Users/Desktop
Classifier: Intended Audience :: System Administrators
Classifier: License :: OSI Approved :: GNU General Public License v3 (GPLv3)
Classifier: Environment :: Console
Classifier: Topic :: Utilities
Classifier: Operating System :: POSIX :: Linux
Classifier: Natural Language :: English
Classifier: Programming Language :: Python :: 3
Classifier: Programming Language :: Python :: 3.5
Classifier: Programming Language :: Python :: 3.6
Classifier: Programming Language :: Python :: 3.7
Classifier: Programming Language :: Python :: 3.8
Classifier: Programming Language :: Python :: 3.9
Classifier: Programming Language :: Unix Shell
Requires-Python: >=3.5
License-File: LICENSE
License-File: COPYING
Requires-Dist: boto3
